pylsat.py
pylsat/__init__.py
pylsat/pylsat.py
vendor/__init__.py
vendor/bolt11/__init__.py
vendor/bolt11/compat.py
vendor/bolt11/core.py
vendor/bolt11/types.py
vendor/bolt11/utils.py
pylsat-0.2.6.dist-info/LICENSE
pylsat-0.2.6.dist-info/METADATA
pylsat-0.2.6.dist-info/WHEEL
pylsat-0.2.6.dist-info/top_level.txt
pylsat-0.2.6.dist-info/RECORD
