Metadata-Version: 2.1
Name: pylsat
Version: 0.2.6
Summary: A Python library for validating L402 (formerly known as LSAT) protocol for Lightning Network payments in a FastAPI application.
Home-page: https://github.com/plebos/pylsat
Author: Tal Shmueli
Author-email: tal@shmueli.org
License: MIT
License-File: LICENSE
Requires-Dist: fastapi
Requires-Dist: starlette
Requires-Dist: pymacaroons
